tap_airlines/__init__.py
tap_airlines/__main__.py
tap_airlines/client.py
tap_airlines/streams.py
tap_airlines/tap.py
tap_airlines/utils.py
tap_airlines/schemas/__init__.py
tap_airlines/schemas/aerolineas_all_flights.json
tap_airlines_arg-1.0.1.dist-info/METADATA
tap_airlines_arg-1.0.1.dist-info/WHEEL
tap_airlines_arg-1.0.1.dist-info/entry_points.txt
tap_airlines_arg-1.0.1.dist-info/licenses/LICENSE
tap_airlines_arg-1.0.1.dist-info/RECORD
