Metadata-Version: 2.4
Name: tap-airlines-arg
Version: 1.0.1
Summary: Singer tap for blueprintdata, built with the Meltano Singer SDK.
Author-email: blueprintdata <juan.rivero@blueprintdata.xyz>
License-Expression: MIT
License-File: LICENSE
Keywords: ELT,blueprintdata
Classifier: Intended Audience :: Developers
Classifier: Operating System :: OS Independent
Classifier: Programming Language :: Python :: 3.10
Classifier: Programming Language :: Python :: 3.11
Classifier: Programming Language :: Python :: 3.12
Classifier: Programming Language :: Python :: 3.13
Classifier: Programming Language :: Python :: 3.14
Requires-Python: >=3.10
Requires-Dist: requests~=2.32.3
Requires-Dist: singer-sdk~=0.53.5
Requires-Dist: typing-extensions>=4.5.0; python_version < '3.13'
Provides-Extra: s3
Requires-Dist: s3fs~=2026.1.0; extra == 's3'
